{
  "entityType" : "NOTIFICATION_RULE",
  "entity" : {
    "additionalConfig" : {
      "description" : "Send notification to tenant admins when any device changes its activity state"
    },
    "enabled" : false,
    "externalId" : {
      "entityType" : "NOTIFICATION_RULE",
      "id" : "47934f90-1713-11f1-a23f-cf49b284c82d"
    },
    "id" : {
      "entityType" : "NOTIFICATION_RULE",
      "id" : "47934f90-1713-11f1-a23f-cf49b284c82d"
    },
    "name" : "Device activity status change",
    "recipientsConfig" : {
      "targets" : [ "478e6d90-1713-11f1-a23f-cf49b284c82d" ],
      "triggerType" : "DEVICE_ACTIVITY"
    },
    "templateId" : {
      "entityType" : "NOTIFICATION_TEMPLATE",
      "id" : "4792b350-1713-11f1-a23f-cf49b284c82d"
    },
    "triggerConfig" : {
      "triggerType" : "DEVICE_ACTIVITY",
      "deviceProfiles" : null,
      "devices" : null,
      "notifyOn" : [ "INACTIVE", "ACTIVE" ],
      "triggerType" : "DEVICE_ACTIVITY"
    },
    "triggerType" : "DEVICE_ACTIVITY"
  }
}